dedup_me/__init__.py
dedup_me/_async.py
dedup_me/_threading.py
dedup_me-0.2.0.dist-info/LICENSE
dedup_me-0.2.0.dist-info/METADATA
dedup_me-0.2.0.dist-info/WHEEL
dedup_me-0.2.0.dist-info/RECORD
