Metadata-Version: 2.1
Name: dedup-me
Version: 0.2.0
Summary: Deduplicate concurrent function calls.
Home-page: https://github.com/ottermata/dedup_me
License: MIT
Keywords: dedup,deduplication,request
Author: Christopher Krause
Author-email: ottermata@pm.me
Requires-Python: >=3.10,<4.0
Classifier: License :: OSI Approved :: MIT License
Classifier: Operating System :: OS Independent
Classifier: Programming Language :: Python
Classifier: Programming Language :: Python :: 3
Classifier: Programming Language :: Python :: 3.10
Classifier: Programming Language :: Python :: 3.11
Classifier: Topic :: Software Development
Classifier: Topic :: Software Development :: Libraries
Classifier: Typing :: Typed
Project-URL: Bug Tracker, https://github.com/ottermata/dedup_me/issues
Project-URL: Repository, https://github.com/ottermata/dedup_me
